README.md
setup.cfg
setup.py
ace_distributions.egg-info/PKG-INFO
ace_distributions.egg-info/SOURCES.txt
ace_distributions.egg-info/dependency_links.txt
ace_distributions.egg-info/not-zip-safe
ace_distributions.egg-info/top_level.txt
distributions/Binomialdistribution.py
distributions/Gaussiandistribution.py
distributions/Generaldistribution.py
distributions/__init__.py